{
    "Ar36": {
        "error": 0.0011956415302018166,
        "error_type": "SEM",
        "filter_outliers_dict": {
            "filter_outliers": true,
            "iterations": 1,
            "std_devs": 3,
            "use_iqr_filtering": false,
            "use_standard_deviation_filtering": false
        },
        "fit": "parabolic",
        "fn": 277,
        "include_baseline_error": true,
        "n": 280,
        "outlier_excluded": [
            98,
            267,
            212
        ],
        "reviewed": true,
        "user_excluded": [],
        "value": 0.23040269346196318
    },
    "Ar37": {
        "error": 0.004152530275008859,
        "error_type": "SEM",
        "filter_outliers_dict": {
            "filter_outliers": true,
            "iterations": 1,
            "std_devs": 3,
            "use_iqr_filtering": false,
            "use_standard_deviation_filtering": false
        },
        "fit": "linear",
        "fn": 278,
        "include_baseline_error": true,
        "n": 280,
        "outlier_excluded": [
            0,
            74
        ],
        "reviewed": true,
        "user_excluded": [],
        "value": 4.732120541205749
    },
    "Ar38": {
        "error": 0.0031139937688545493,
        "error_type": "SEM",
        "filter_outliers_dict": {
            "filter_outliers": true,
            "iterations": 1,
            "std_devs": 3,
            "use_iqr_filtering": false,
            "use_standard_deviation_filtering": false
        },
        "fit": "linear",
        "fn": 279,
        "include_baseline_error": true,
        "n": 280,
        "outlier_excluded": [
            233
        ],
        "reviewed": true,
        "user_excluded": [],
        "value": 0.36462597452101997
    },
    "Ar39": {
        "error": 0.014325627072466743,
        "error_type": "SEM",
        "filter_outliers_dict": {
            "filter_outliers": true,
            "iterations": 1,
            "std_devs": 3,
            "use_iqr_filtering": false,
            "use_standard_deviation_filtering": false
        },
        "fit": "parabolic",
        "fn": 279,
        "include_baseline_error": true,
        "n": 280,
        "outlier_excluded": [
            113
        ],
        "reviewed": true,
        "user_excluded": [],
        "value": 24.553188174503838
    },
    "Ar40": {
        "error": 0.01785661573776965,
        "error_type": "SEM",
        "filter_outliers_dict": {
            "filter_outliers": true,
            "iterations": 1,
            "std_devs": 3,
            "use_iqr_filtering": false,
            "use_standard_deviation_filtering": false
        },
        "fit": "parabolic",
        "fn": 280,
        "include_baseline_error": true,
        "n": 280,
        "outlier_excluded": [],
        "reviewed": true,
        "user_excluded": [],
        "value": 69.94344461685051
    },
    "Ar41": {
        "error": 0.035678058512541154,
        "error_type": "SEM",
        "filter_outliers_dict": {
            "filter_outliers": true,
            "iterations": 1,
            "std_devs": 2
        },
        "fit": "linear",
        "value": -0.3372086597111006
    }
}