{
    "AX": {
        "error": 0.009096581099831596,
        "error_type": "SEM",
        "filter_outliers_dict": {
            "filter_outliers": true,
            "iterations": 1,
            "std_devs": 3,
            "use_iqr_filtering": false,
            "use_standard_deviation_filtering": false
        },
        "fit": "average",
        "fn": 45,
        "include_baseline_error": true,
        "n": 45,
        "outlier_excluded": [],
        "reviewed": true,
        "user_excluded": [],
        "value": 0.10985850286670029
    },
    "CDD": {
        "error": 3.4086803983276094e-06,
        "error_type": "SEM",
        "filter_outliers_dict": {
            "filter_outliers": true,
            "iterations": 1,
            "std_devs": 10,
            "use_iqr_filtering": false,
            "use_standard_deviation_filtering": false
        },
        "fit": "average",
        "fn": 45,
        "include_baseline_error": true,
        "n": 45,
        "outlier_excluded": [],
        "reviewed": true,
        "user_excluded": [],
        "value": 3.408680398327609e-06
    },
    "H1": {
        "error": 0.008095132199722625,
        "error_type": "SEM",
        "filter_outliers_dict": {
            "filter_outliers": true,
            "iterations": 1,
            "std_devs": 3,
            "use_iqr_filtering": false,
            "use_standard_deviation_filtering": false
        },
        "fit": "average",
        "fn": 45,
        "include_baseline_error": true,
        "n": 45,
        "outlier_excluded": [],
        "reviewed": true,
        "user_excluded": [],
        "value": 0.0304194034762784
    },
    "H2": {
        "error": 0.039495956808472364,
        "error_type": "SEM",
        "filter_outliers_dict": {
            "filter_outliers": true,
            "iterations": 1,
            "std_devs": 2
        },
        "fit": "average",
        "value": -0.3167815191312118
    },
    "L1": {
        "error": 0.003949418685465212,
        "error_type": "SEM",
        "filter_outliers_dict": {
            "filter_outliers": true,
            "iterations": 1,
            "std_devs": 3,
            "use_iqr_filtering": false,
            "use_standard_deviation_filtering": false
        },
        "fit": "average",
        "fn": 45,
        "include_baseline_error": true,
        "n": 45,
        "outlier_excluded": [],
        "reviewed": true,
        "user_excluded": [],
        "value": 0.02460178320373719
    },
    "L2": {
        "error": 0.0049159665705770916,
        "error_type": "SEM",
        "filter_outliers_dict": {
            "filter_outliers": true,
            "iterations": 1,
            "std_devs": 3,
            "use_iqr_filtering": false,
            "use_standard_deviation_filtering": false
        },
        "fit": "average",
        "fn": 45,
        "include_baseline_error": true,
        "n": 45,
        "outlier_excluded": [],
        "reviewed": true,
        "user_excluded": [],
        "value": -0.02388527625654307
    }
}