{
    "Ar36": {
        "error": 0.00023097458720801716,
        "error_type": "",
        "fit": "previous",
        "references": [
            {
                "exclude": false,
                "record_id": "bu-FC-J-17060"
            }
        ],
        "value": 0.014122817176991145
    },
    "Ar37": {
        "error": 0.004552001276666404,
        "error_type": "",
        "fit": "previous",
        "references": [
            {
                "exclude": false,
                "record_id": "bu-FC-J-17060"
            }
        ],
        "value": 0.0445948921625178
    },
    "Ar38": {
        "error": 0.0037086681679631465,
        "error_type": "",
        "fit": "previous",
        "references": [
            {
                "exclude": false,
                "record_id": "bu-FC-J-17060"
            }
        ],
        "value": 0.04534993292328019
    },
    "Ar39": {
        "error": 0.019842504196547695,
        "error_type": "",
        "fit": "previous",
        "references": [
            {
                "exclude": false,
                "record_id": "bu-FC-J-17060"
            }
        ],
        "value": 0.12223616188605846
    },
    "Ar40": {
        "error": 0.016868807455854805,
        "error_type": "",
        "fit": "previous",
        "references": [
            {
                "exclude": false,
                "record_id": "bu-FC-J-17060"
            }
        ],
        "value": 1.5000111120839623
    },
    "Ar41": {
        "error": 0.02113188562103394,
        "error_type": "",
        "fit": "previous",
        "references": [
            {
                "exclude": false,
                "record_id": "bu-FC-J-17060"
            }
        ],
        "value": 0.09374290134242982
    }
}