{
    "Ar36": {
        "error": 0.00043618319703928645, 
        "filter_outliers_dict": {
            "filter_outliers": true, 
            "iterations": 2, 
            "std_devs": 2
        }, 
        "fit": "Parabolic", 
        "value": 0.052595342129533575
    }, 
    "Ar37": {
        "error": 0.011876586864750821, 
        "filter_outliers_dict": {
            "filter_outliers": true, 
            "iterations": 2, 
            "std_devs": 2
        }, 
        "fit": "linear", 
        "value": 0.7602692608656266
    }, 
    "Ar38": {
        "error": 0.012771502233972146, 
        "filter_outliers_dict": {
            "filter_outliers": true, 
            "iterations": 2, 
            "std_devs": 2
        }, 
        "fit": "linear", 
        "value": 0.12571071515522472
    }, 
    "Ar39": {
        "error": 0.023023075070401175, 
        "filter_outliers_dict": {
            "filter_outliers": true, 
            "iterations": 2, 
            "std_devs": 2
        }, 
        "fit": "Parabolic", 
        "value": 17.537811336163557
    }, 
    "Ar40": {
        "error": 0.02003381661356843, 
        "filter_outliers_dict": {
            "filter_outliers": true, 
            "iterations": 2, 
            "std_devs": 2
        }, 
        "fit": "Parabolic", 
        "value": 19.78716452063751
    }
}