{
    "Ar36": {
        "error": 0.004824832918612079, 
        "filter_outliers_dict": {
            "filter_outliers": true, 
            "iterations": 2, 
            "std_devs": 2
        }, 
        "fit": "Parabolic", 
        "value": 4.078820752246008
    }, 
    "Ar37": {
        "error": 0.011167218628761006, 
        "filter_outliers_dict": {
            "filter_outliers": true, 
            "iterations": 2, 
            "std_devs": 2
        }, 
        "fit": "linear", 
        "value": -0.06718912602360674
    }, 
    "Ar38": {
        "error": 0.0126573548087999, 
        "filter_outliers_dict": {
            "filter_outliers": true, 
            "iterations": 2, 
            "std_devs": 2
        }, 
        "fit": "linear", 
        "value": 0.6830416948700904
    }, 
    "Ar39": {
        "error": 0.025181629746098364, 
        "filter_outliers_dict": {
            "filter_outliers": true, 
            "iterations": 2, 
            "std_devs": 2
        }, 
        "fit": "Parabolic", 
        "value": 0.04538517268244823
    }, 
    "Ar40": {
        "error": 0.09705691651858789, 
        "filter_outliers_dict": {
            "filter_outliers": true, 
            "iterations": 2, 
            "std_devs": 2
        }, 
        "fit": "Parabolic", 
        "value": 1250.2945480547633
    }
}