{
    "AX": {
        "error": 0.004379284755653847, 
        "filter_outliers_dict": {
            "filter_outliers": true, 
            "iterations": 1, 
            "std_devs": 2
        }, 
        "fit": "average", 
        "value": 0.07250954749542994
    }, 
    "CDD": {
        "error": 6.306463310588845e-06, 
        "filter_outliers_dict": {
            "filter_outliers": true, 
            "iterations": 1, 
            "std_devs": 10
        }, 
        "fit": "average", 
        "value": 3.0024770862069224e-05
    }, 
    "H1": {
        "error": 0.003703436251883955, 
        "filter_outliers_dict": {
            "filter_outliers": true, 
            "iterations": 1, 
            "std_devs": 2
        }, 
        "fit": "average", 
        "value": -0.036073503051698735
    }, 
    "H2": {
        "error": 0.0038829139622252244, 
        "filter_outliers_dict": {
            "filter_outliers": true, 
            "iterations": 1, 
            "std_devs": 2
        }, 
        "fit": "average", 
        "value": 0.07272957389399128
    }, 
    "L1": {
        "error": 0.0020129715584229005, 
        "filter_outliers_dict": {
            "filter_outliers": true, 
            "iterations": 1, 
            "std_devs": 2
        }, 
        "fit": "average", 
        "value": -0.004295854240120032
    }, 
    "L2": {
        "error": 0.00428299030362021, 
        "filter_outliers_dict": {
            "filter_outliers": true, 
            "iterations": 1, 
            "std_devs": 2
        }, 
        "fit": "average", 
        "value": 0.14667107143573882
    }
}