{
    "Ar36": {
        "error": 0.00020407285565736258,
        "error_type": "",
        "fit": "previous",
        "references": [
            {
                "exclude": false,
                "record_id": "bu-FC-J-16955"
            }
        ],
        "value": 0.010050311926467681
    },
    "Ar37": {
        "error": 0.004648781975321735,
        "error_type": "",
        "fit": "previous",
        "references": [
            {
                "exclude": false,
                "record_id": "bu-FC-J-16955"
            }
        ],
        "value": 0.03242371032368778
    },
    "Ar38": {
        "error": 0.004607162271063801,
        "error_type": "",
        "fit": "previous",
        "references": [
            {
                "exclude": false,
                "record_id": "bu-FC-J-16955"
            }
        ],
        "value": 0.02116127779966321
    },
    "Ar39": {
        "error": 0.018392601837512308,
        "error_type": "",
        "fit": "previous",
        "references": [
            {
                "exclude": false,
                "record_id": "bu-FC-J-16955"
            }
        ],
        "value": 0.0644099828844002
    },
    "Ar40": {
        "error": 0.018235316616759152,
        "error_type": "",
        "fit": "previous",
        "references": [
            {
                "exclude": false,
                "record_id": "bu-FC-J-16955"
            }
        ],
        "value": 1.2296659193473702
    },
    "Ar41": {
        "error": 0.02183719310970743,
        "error_type": "",
        "fit": "previous",
        "references": [
            {
                "exclude": false,
                "record_id": "bu-FC-J-16955"
            }
        ],
        "value": 0.07182474925356863
    }
}